{"Id":"1db4b17b-7374-40c1-9f30-e80bd58d1022","LogDateUtc":"2017-03-17T13:51:43.8053596Z","IpAddress":"127.0.0.1","Culture":"en-US","Url":"/csscsr/commentjs","ShortUrl":"/csscsr/commentjs","Thread":"","LogLevel":"Information","Logger":"Microsoft.AspNetCore.Mvc.Internal.ControllerActionInvoker","Message":"Executed action cloudscribe.SimpleContent.Web.Controllers.csscsrController.commentjs (cloudscribe.SimpleContent.Web) in 32.7448ms","StateJson":"[{\"Key\":\"ActionName\",\"Value\":\"cloudscribe.SimpleContent.Web.Controllers.csscsrController.commentjs (cloudscribe.SimpleContent.Web)\"},{\"Key\":\"ElapsedMilliseconds\",\"Value\":32.744800000000005},{\"Key\":\"{OriginalFormat}\",\"Value\":\"Executed action {ActionName} in {ElapsedMilliseconds}ms\"}]","EventId":2}