{"Id":"277e906c-078c-4111-8dcc-a7c11799bdad","LogDateUtc":"2017-03-17T13:46:36.4440304Z","IpAddress":"127.0.0.1","Culture":"en-US","Url":"/cscsr/requiredwhenvalidator","ShortUrl":"/cscsr/requiredwhenvalidator","Thread":"","LogLevel":"Information","Logger":"Microsoft.AspNetCore.Mvc.Internal.ControllerActionInvoker","Message":"Executing action method cloudscribe.Core.Web.Controllers.cscsrController.requiredwhenvalidator (cloudscribe.Core.Web) with arguments ((null)) - ModelState is Valid","StateJson":"[{\"Key\":\"ActionName\",\"Value\":\"cloudscribe.Core.Web.Controllers.cscsrController.requiredwhenvalidator (cloudscribe.Core.Web)\"},{\"Key\":\"Arguments\",\"Value\":null},{\"Key\":\"ValidationState\",\"Value\":2},{\"Key\":\"{OriginalFormat}\",\"Value\":\"Executing action method {ActionName} with arguments ({Arguments}) - ModelState is {ValidationState}\"}]","EventId":1}