{"Id":"5da2b834-8a5f-4e1a-b239-6717448d5aeb","LogDateUtc":"2017-03-13T15:09:42.9772931Z","IpAddress":"127.0.0.1","Culture":"en-US","Url":"/blog/","ShortUrl":"/blog/","Thread":"","LogLevel":"Information","Logger":"Microsoft.AspNetCore.Mvc.Internal.ControllerActionInvoker","Message":"Executing action method cloudscribe.SimpleContent.Web.Controllers.BlogController.Index (cloudscribe.SimpleContent.Web) with arguments (, 1) - ModelState is Valid","StateJson":"[{\"Key\":\"ActionName\",\"Value\":\"cloudscribe.SimpleContent.Web.Controllers.BlogController.Index (cloudscribe.SimpleContent.Web)\"},{\"Key\":\"Arguments\",\"Value\":[\"\",\"1\"]},{\"Key\":\"ValidationState\",\"Value\":2},{\"Key\":\"{OriginalFormat}\",\"Value\":\"Executing action method {ActionName} with arguments ({Arguments}) - ModelState is {ValidationState}\"}]","EventId":1}