{"Id":"656de124-a2b0-40d5-a684-4f273cf44b9e","LogDateUtc":"2017-03-13T15:10:22.2078203Z","IpAddress":"127.0.0.1","Culture":"en-US","Url":"/blog/edit","ShortUrl":"/blog/edit","Thread":"","LogLevel":"Information","Logger":"Microsoft.AspNetCore.Mvc.Internal.ControllerActionInvoker","Message":"Executed action cloudscribe.SimpleContent.Web.Controllers.BlogController.Edit (cloudscribe.SimpleContent.Web) in 699.4562ms","StateJson":"[{\"Key\":\"ActionName\",\"Value\":\"cloudscribe.SimpleContent.Web.Controllers.BlogController.Edit (cloudscribe.SimpleContent.Web)\"},{\"Key\":\"ElapsedMilliseconds\",\"Value\":699.45620000000008},{\"Key\":\"{OriginalFormat}\",\"Value\":\"Executed action {ActionName} in {ElapsedMilliseconds}ms\"}]","EventId":2}