{"Id":"ba7ea058-555d-432b-9b7b-f404c30ce7bb","LogDateUtc":"2017-03-13T15:09:13.7231079Z","IpAddress":"127.0.0.1","Culture":"en-US","Url":"/csscsr/blogcommoncss","ShortUrl":"/csscsr/blogcommoncss","Thread":"","LogLevel":"Information","Logger":"Microsoft.AspNetCore.Mvc.Internal.ControllerActionInvoker","Message":"Executed action cloudscribe.SimpleContent.Web.Controllers.csscsrController.blogcommoncss (cloudscribe.SimpleContent.Web) in 54.5483ms","StateJson":"[{\"Key\":\"ActionName\",\"Value\":\"cloudscribe.SimpleContent.Web.Controllers.csscsrController.blogcommoncss (cloudscribe.SimpleContent.Web)\"},{\"Key\":\"ElapsedMilliseconds\",\"Value\":54.548300000000005},{\"Key\":\"{OriginalFormat}\",\"Value\":\"Executed action {ActionName} in {ElapsedMilliseconds}ms\"}]","EventId":2}