{"Id":"df2b5791-56cc-4bbb-a6e7-22f7ad0030f8","LogDateUtc":"2017-03-20T18:50:04.2621192Z","IpAddress":"127.0.0.1","Culture":"en-US","Url":"/csscsr/blogcommoncss","ShortUrl":"/csscsr/blogcommoncss","Thread":"","LogLevel":"Information","Logger":"Microsoft.AspNetCore.Mvc.Internal.ControllerActionInvoker","Message":"Executed action cloudscribe.SimpleContent.Web.Controllers.csscsrController.blogcommoncss (cloudscribe.SimpleContent.Web) in 21.7335ms","StateJson":"[{\"Key\":\"ActionName\",\"Value\":\"cloudscribe.SimpleContent.Web.Controllers.csscsrController.blogcommoncss (cloudscribe.SimpleContent.Web)\"},{\"Key\":\"ElapsedMilliseconds\",\"Value\":21.7335},{\"Key\":\"{OriginalFormat}\",\"Value\":\"Executed action {ActionName} in {ElapsedMilliseconds}ms\"}]","EventId":2}